TELUS_NFV_Taranis/__init__.py
TELUS_NFV_Taranis/dispatcher.py
TELUS_NFV_Taranis/message_schemas.py
telus_nfv_taranis-0.0.11.dist-info/LICENSE
telus_nfv_taranis-0.0.11.dist-info/WHEEL
telus_nfv_taranis-0.0.11.dist-info/METADATA
telus_nfv_taranis-0.0.11.dist-info/RECORD
